afro/__init__.py
afro/afro.py
afroy-0.0.9.dist-info/LICENSE
afroy-0.0.9.dist-info/METADATA
afroy-0.0.9.dist-info/WHEEL
afroy-0.0.9.dist-info/top_level.txt
afroy-0.0.9.dist-info/RECORD
