Metadata-Version: 2.1
Name: afroy
Version: 0.0.9
Summary: Simplifies some tasks
Home-page: https://github.com/AfroYousef/adt
Author: Yousef Abdelkader
Author-email: yousef.mkader@gmail.com
License: UNKNOWN
Platform: UNKNOWN
Classifier: Programming Language :: Python :: 3
Classifier: License :: OSI Approved :: MIT License
Classifier: Operating System :: OS Independent
Requires-Python: >=3.6
Requires-Dist: termcolor
